setup.py
mypypackagemoty/my.py
mypypackagemoty.egg-info/PKG-INFO
mypypackagemoty.egg-info/SOURCES.txt
mypypackagemoty.egg-info/dependency_links.txt
mypypackagemoty.egg-info/top_level.txt